dxp/__init__.py
dxp/cli.py
dxp/lab.py
dxp/util.py
dxp-0.1.1.data/scripts/dplt
dxp-0.1.1.data/scripts/tpose
dxp-0.1.1.dist-info/METADATA
dxp-0.1.1.dist-info/WHEEL
dxp-0.1.1.dist-info/entry_points.txt
dxp-0.1.1.dist-info/top_level.txt
dxp-0.1.1.dist-info/RECORD
