Metadata-Version: 2.1
Name: dxp
Version: 0.1.1
Summary: Library for analyzing CSV data
Home-page: https://github.com/jmdaemon/dxp
Author: Joseph Diza
Author-email: josephm.diza@gmail.com
License: MIT
Project-URL: Bug Tracker, https://github.com/jmdaemon/dxp/issues
Platform: UNKNOWN
Classifier: Programming Language :: Python :: 3
Classifier: License :: OSI Approved :: MIT License
Classifier: Operating System :: OS Independent
Requires-Python: >=3.6
Requires-Dist: argparse
